goodenough.py
goodenough-0.0.2.dist-info/METADATA
goodenough-0.0.2.dist-info/WHEEL
goodenough-0.0.2.dist-info/top_level.txt
goodenough-0.0.2.dist-info/RECORD
