Metadata-Version: 2.1
Name: goodenough
Version: 0.0.2
Summary: Lib to pick the "best" item from a random sample
Home-page: https://github.com/marcgurevitx/goodenough
Author: Marc Gurevitx
Author-email: marcgurevitx@gmail.com
License: The Unlicense
Platform: UNKNOWN
Provides-Extra: web
Requires-Dist: aiohttp[speedups] ; extra == 'web'
